vector3/__init__.py
vector3/vector.py
vector3-1.0.0.dist-info/licenses/LICENSE
vector3-1.0.0.dist-info/METADATA
vector3-1.0.0.dist-info/WHEEL
vector3-1.0.0.dist-info/top_level.txt
vector3-1.0.0.dist-info/RECORD
