Metadata-Version: 2.4
Name: vector3
Version: 1.0.0
Summary: A flexible 3D vector math library supporting lower dimensions
Author-email: Bhavesh Ganolia <ganoliabhavesh@gmail.com>
License: MIT
Keywords: vector,math,geometry,linear-algebra,3d
Classifier: Programming Language :: Python :: 3
Classifier: License :: OSI Approved :: MIT License
Classifier: Operating System :: OS Independent
Classifier: Topic :: Scientific/Engineering :: Mathematics
Requires-Python: >=3.8
License-File: LICENSE
Dynamic: license-file
